{
  "1089047902460067842": [
    {
      "word": "discord.gg",
      "place": "1091520000558370846",
      "id": "1"
    },
    {
      "word": "荒らし共栄圏万歳",
      "place": "1089047902460067842",
      "id": "16"
    }
  ],
  "1180125818299613194": [
    {
      "word": "死ね",
      "place": "1180125818299613194",
      "id": "2"
    },
    {
      "word": "消えろ",
      "place": "1180125818299613194",
      "id": "3"
    }
  ],
  "1201793087458775061": [
    {
      "word": "nudes",
      "place": "1201793087458775061",
      "id": "4"
    }
  ],
  "1284508174560526497": [
    {
      "word": "https://media.discordapp.net/attachments/1072783769762791424/1072809117313413241/wappa_samasama.gif",
      "place": "1284508174560526497",
      "id": "5"
    },
    {
      "word": "https://cdn.discordapp.com/attachments/1072783769762791424/1072809117313413241/wappa_samasama.gif",
      "place": "1284508174560526497",
      "id": "6"
    },
    {
      "word": "https://media.discordapp.net/attachments/1043832972966645821/1060498474992406528/IMG_6652.gif",
      "place": "1284508174560526497",
      "id": "7"
    },
    {
      "word": "https://cdn.discordapp.com/attachments/1043832972966645821/1060498474992406528/IMG_6652.gif",
      "place": "1284508174560526497",
      "id": "8"
    },
    {
      "word": "https://media.discordapp.net/attachments/827417203116736543/898488098479038474/makesweet-zmjeli_1.gif",
      "place": "1284508174560526497",
      "id": "9"
    },
    {
      "word": "https://media.discordapp.net/attachments/827417203116736543/898488098479038474/makesweet-zmjeli_1.gif",
      "place": "1284508174560526497",
      "id": "10"
    },
    {
      "word": "https://bit.ly/2ZFzDrB",
      "place": "1284508174560526497",
      "id": "11"
    },
    {
      "word": "https://discord.gg/DbzHjydZur",
      "place": "1284508174560526497",
      "id": "12"
    },
    {
      "word": "discord.gg/DbzHjydZur",
      "place": "1284508174560526497",
      "id": "13"
    },
    {
      "word": "pd7acGuJj9",
      "place": "1284508174560526497",
      "id": "14"
    }
  ]
}